czbenchmarks/__init__.py
czbenchmarks/constants.py
czbenchmarks/exceptions.py
czbenchmarks/file_cache.py
czbenchmarks/file_utils.py
czbenchmarks/types.py
czbenchmarks/utils.py
czbenchmarks/cli/__init__.py
czbenchmarks/cli/cli.py
czbenchmarks/cli/cli_list.py
czbenchmarks/cli/utils.py
czbenchmarks/conf/datasets.yaml
czbenchmarks/conf/datasets_deprecated.yaml
czbenchmarks/datasets/README.md
czbenchmarks/datasets/__init__.py
czbenchmarks/datasets/dataset.py
czbenchmarks/datasets/single_cell.py
czbenchmarks/datasets/single_cell_labeled.py
czbenchmarks/datasets/single_cell_perturbation.py
czbenchmarks/datasets/types.py
czbenchmarks/datasets/utils.py
czbenchmarks/datasets/utils_single_cell.py
czbenchmarks/datasets/validators/__init__.py
czbenchmarks/datasets/validators/dataset_validator.py
czbenchmarks/datasets/validators/single_cell_validator.py
czbenchmarks/metrics/README.md
czbenchmarks/metrics/__init__.py
czbenchmarks/metrics/implementations.py
czbenchmarks/metrics/types.py
czbenchmarks/metrics/utils.py
czbenchmarks/tasks/README.md
czbenchmarks/tasks/__init__.py
czbenchmarks/tasks/clustering.py
czbenchmarks/tasks/constants.py
czbenchmarks/tasks/embedding.py
czbenchmarks/tasks/integration.py
czbenchmarks/tasks/label_prediction.py
czbenchmarks/tasks/sequential.py
czbenchmarks/tasks/task.py
czbenchmarks/tasks/types.py
czbenchmarks/tasks/utils.py
czbenchmarks/tasks/single_cell/__init__.py
czbenchmarks/tasks/single_cell/cross_species_integration.py
czbenchmarks/tasks/single_cell/cross_species_label_prediction.py
czbenchmarks/tasks/single_cell/perturbation_expression_prediction.py
cz_benchmarks-0.15.0.dist-info/METADATA
cz_benchmarks-0.15.0.dist-info/WHEEL
cz_benchmarks-0.15.0.dist-info/entry_points.txt
cz_benchmarks-0.15.0.dist-info/licenses/LICENSE.md
cz_benchmarks-0.15.0.dist-info/RECORD
